caption_project-0.1.12.dist-info/METADATA
caption_project-0.1.12.dist-info/WHEEL
caption_project/caption.py
caption_project/image.py
caption_project/py.typed
caption_project/_lowlevel.pyi
caption_project/__init__.py
caption_project/_lowlevel.cp39-win32.pyd
caption_project-0.1.12.dist-info/RECORD
